{
  "phase1": {
    "1": {
      "type": "talk",
      "dialogue": "約束しろ。もう会いにこないと。",
      "background": "bg055_f",
      "bgm": "9",
      "char": "m038_00",
      "speaker": "same_full"
    },
    "2": {
      "type": "talk",
      "dialogue": "……",
      "char": "m038_01",
      "speaker": "same",
      "pos": "left"
    },
    "3": {
      "type": "talk",
      "dialogue": "返事は。",
      "char": "m038_00",
      "speaker": "same_full",
      "pos": "right"
    },
    "4": {
      "type": "talk",
      "dialogue": "…イヤだ。",
      "char": "m038_01",
      "speaker": "same",
      "pos": "left"
    },
    "5": {
      "type": "talk",
      "dialogue": "やれやれ…\\契約者に似たのか、忠誠心だけは強いな。\\おい、お前の主人は俺じゃないぞ。",
      "char": "m038_00",
      "speaker": "same_full",
      "pos": "right"
    },
    "6": {
      "type": "talk",
      "dialogue": "まあ…全部が気に入ったわけじゃないが、\\仕方ないだろ。お前の名前が書かれた契約書は、\\奴の手にあるんだ。",
      "char": "keep",
      "speaker": "same_full",
      "pos": "right"
    },
    "7": {
      "type": "talk",
      "dialogue": "そもそも、チャイルドが悪魔じゃなく契約者を\\主人として仕える理由はなんだ？",
      "char": "keep",
      "speaker": "same_full",
      "pos": "right"
    },
    "8": {
      "type": "talk",
      "dialogue": "……",
      "char": "m038_01",
      "speaker": "same",
      "pos": "left"
    },
    "9": {
      "type": "talk",
      "dialogue": "はあ…もどかしい。一体何を考えているんだか。\\こんなのが俺の中から出て来たってホントかよ。",
      "char": "m038_00",
      "speaker": "same_full",
      "pos": "right"
    },
    "10": {
      "type": "talk",
      "dialogue": "…オマエが一番、最初だっタ。",
      "char": "m038_01",
      "speaker": "same",
      "pos": "left"
    },
    "11": {
      "type": "talk",
      "dialogue": "何？",
      "char": "m038_00",
      "speaker": "same_full",
      "pos": "right"
    },
    "12": {
      "type": "talk",
      "dialogue": "生まれテ、一番最初に…お前と会っタ。",
      "char": "m038_01",
      "speaker": "same",
      "pos": "left"
    },
    "13": {
      "type": "talk",
      "dialogue": "俺と？悪魔じゃなくて？そういうもんなのか？\\悪魔じゃないからわからんな。",
      "char": "m038_00",
      "speaker": "same_full",
      "pos": "right"
    },
    "14": {
      "type": "talk",
      "dialogue": "で、それが理由か？鳥のヒナみたいだな。\\最初に目にした奴が親ってか？",
      "char": "keep",
      "speaker": "same_full",
      "pos": "right"
    },
    "15": {
      "type": "talk",
      "dialogue": "…オレが、気にイら…ないのカ？",
      "char": "m038_01",
      "speaker": "same",
      "pos": "left"
    },
    "16": {
      "type": "talk",
      "dialogue": "…ああ、そうだ。俺のチャイルドのくせに、\\不細工すぎる。俺にちっとも似ていない。",
      "char": "m038_00",
      "speaker": "same_full",
      "pos": "right"
    },
    "17": {
      "type": "talk",
      "dialogue": "…違ウ…オレたち、似てル。",
      "char": "m038_01",
      "speaker": "same",
      "pos": "left"
    },
    "18": {
      "type": "talk",
      "dialogue": "はあ？おい、よく見ろよ。一体どこが似て…",
      "char": "m038_00",
      "speaker": "same_full",
      "pos": "right"
    },
    "19": {
      "type": "talk",
      "dialogue": "オレ…オマエの欲望を知ってル。",
      "char": "m038_01",
      "speaker": "same",
      "distance": "near"
    },
    "20": {
      "type": "talk",
      "dialogue": "……俺の欲望？なんだそりゃ？",
      "char": "m038_00",
      "speaker": "same_full",
      "pos": "right"
    },
    "21": {
      "type": "talk",
      "dialogue": "…オマエがしたイ、すべテのこト。",
      "char": "m038_01",
      "speaker": "same",
      "pos": "left"
    },
    "22": {
      "type": "talk",
      "dialogue": "はは、なんだそりゃ…一体何の話だよ？",
      "char": "m038_00",
      "speaker": "same_full",
      "pos": "right"
    },
    "23": {
      "type": "talk",
      "dialogue": "ソレ…オレにしカわからなイ…\\オレは「オマエの」チャイルドだかラ。\\オマエが祓魔師だったかラ…押し殺しタ、欲望。",
      "char": "m038_01",
      "speaker": "same",
      "pos": "left"
    },
    "24": {
      "type": "talk",
      "dialogue": "それガ、オレ。",
      "char": "keep",
      "speaker": "same",
      "distance": "near"
    },
    "25": {
      "type": "talk",
      "dialogue": "…だからこんなに不細工なのか？",
      "char": "m038_00",
      "speaker": "same_full",
      "pos": "right"
    },
    "26": {
      "type": "talk",
      "dialogue": "まあ、いいだろう。お前ほど、俺を良く知る奴は\\いないってことは認める。だけどな、\\なら、なおのこと困るんだよ、この馬鹿が。",
      "char": "keep",
      "speaker": "same",
      "pos": "right"
    },
    "27": {
      "type": "talk",
      "dialogue": "…？",
      "char": "m038_01",
      "speaker": "same",
      "pos": "left"
    },
    "28": {
      "type": "talk",
      "dialogue": "手下が主人の秘密をたくさん知ってて\\いい事ないだろ？\\いつ裏切られるかわかったもんじゃない。",
      "char": "m038_00",
      "speaker": "same_full",
      "pos": "right"
    },
    "29": {
      "type": "talk",
      "dialogue": "だったらな…いっそ、友達になろうぜ。",
      "char": "keep",
      "speaker": "same",
      "pos": "right",
      "distance": "near"
    },
    "30": {
      "type": "talk",
      "dialogue": "…ともだチ？",
      "char": "m038_01",
      "speaker": "same",
      "pos": "left",
      "one_ani": "attack"
    },
    "31": {
      "type": "talk",
      "dialogue": "友達なら、弱点を打ち明けても関係ないだろ？\\いや、まともな友達がいないから、\\俺もよくわからんが…",
      "char": "m038_00",
      "speaker": "same_full",
      "pos": "right"
    },
    "32": {
      "type": "talk",
      "dialogue": "そもそも、お前は俺の欲望そのものだってことだし\\友達ってのも違うだろうけど…\\ま、細かいことはいいだろ。",
      "char": "keep",
      "speaker": "same_full",
      "pos": "right"
    },
    "33": {
      "type": "talk",
      "dialogue": "…ともだチ。",
      "char": "m038_01",
      "speaker": "same",
      "pos": "left",
      "one_ani": "attack"
    },
    "34": {
      "type": "talk",
      "dialogue": "ああ。わかったな？これからは主人じゃないぞ？",
      "char": "m038_00",
      "speaker": "same_full",
      "pos": "right"
    },
    "35": {
      "type": "talk",
      "dialogue": "……",
      "char": "m038_01",
      "speaker": "same",
      "pos": "left"
    },
    "36": {
      "type": "curtain",
      "background": "back",
      "fade_out": "normal",
      "wait": "normal",
      "fade_in": "normal"
    }
  }
}