{
  "phase1": {
    "1": {
      "type": "talk",
      "dialogue": "観念しろよ、フレイ！\\もう逃げるところもないだろ？",
      "background": "bg198_f",
      "bgm": "9",
      "char": "c000_01",
      "speaker": "same",
      "pos": "left",
      "facial": "angry",
      "voiceid": "104803001"
    },
    "2": {
      "type": "talk",
      "dialogue": "そうだな。\\ここまで簡単に<color=ff9900>《誘導》</color>できるとは思わなかったぞ、このバカが。",
      "char": "c051_02",
      "speaker": "same",
      "pos": "right",
      "voiceid": "104803002"
    },
    "3": {
      "type": "talk",
      "dialogue": "ここまで追い込まれてるのに、\\まだ戦略だとか言い張る気か？",
      "char": "c000_01",
      "speaker": "same",
      "pos": "left",
      "facial": "haah",
      "voiceid": "104803003"
    },
    "4": {
      "type": "talk",
      "dialogue": "当たり前だ。\\ボロボロの補欠がっ！",
      "char": "c051_02",
      "speaker": "same",
      "pos": "right",
      "distance": "near",
      "voiceid": "104803004"
    },
    "5": {
      "type": "curtain",
      "background": "back",
      "fade_out": "normal",
      "wait": "normal"
    }
  }
}