{
  "phase1": {
    "1": {
      "type": "talk",
      "dialogue": "<color=ff1493>エトワール！",
      "background": "e048_01_f",
      "bgm": "4",
      "char": "c107_02",
      "speaker": "same",
      "distance": "near",
      "mvd": "ux/battle/sfx_enchant.mvd|boom_start"
    },
    "2": {
      "type": "talk",
      "dialogue": "はぁ。",
      "background": "bg086_f",
      "char": "c001_01",
      "speaker": "same",
      "pos": "right",
      "distance": "normal",
      "facial": "confused"
    },
    "3": {
      "type": "talk",
      "dialogue": "いつも俺をからかい遊んでいるモナが、ああやって\\困っている顔をするのは珍しい…",
      "char": "none",
      "speaker": "none",
      "screen_effect": "dark"
    },
    "4": {
      "type": "talk",
      "dialogue": "ふん！いい気味だ。",
      "char": "none",
      "speaker": "none",
      "screen_effect": "dark"
    },
    "5": {
      "type": "talk",
      "dialogue": "しかし！そろそろこの辺でやめておかないとモナは\\きっと怒りを爆発させるだろう。",
      "char": "none",
      "speaker": "none",
      "screen_effect": "dark"
    },
    "6": {
      "type": "talk",
      "dialogue": "おい！\\そこの興奮したヒマワリ！",
      "char": "c000_01",
      "speaker": "same",
      "pos": "left",
      "facial": "fury",
      "before_effect": "shake"
    },
    "7": {
      "type": "talk",
      "dialogue": "<color=ff1493>イエッサー！",
      "char": "c107_01",
      "speaker": "same",
      "pos": "right",
      "distance": "normal"
    },
    "8": {
      "type": "talk",
      "dialogue": "うちの女王様をいじめるのはやめにして、\\呼んでもいないのに来た理由を教えてくれ！",
      "char": "c000_01",
      "speaker": "same",
      "pos": "left"
    },
    "9": {
      "type": "talk",
      "dialogue": "<color=ff1493>あ、そのことですが…<color=ff1493>",
      "char": "c107_01",
      "speaker": "same",
      "pos": "right",
      "distance": "near"
    },
    "10": {
      "type": "talk",
      "dialogue": "ひぃ…",
      "char": "c000_01",
      "speaker": "same",
      "pos": "left",
      "facial": "nonsense",
      "before_effect": "shake"
    },
    "11": {
      "type": "talk",
      "dialogue": "<color=ff1493>ゴッドファーザーの\\<color=ff1493>チャイルドになれたことは嬉しいのですが、\\<color=ff1493>もう少し刺激が必要です。",
      "char": "c107_01",
      "speaker": "same",
      "pos": "right",
      "distance": "near"
    },
    "12": {
      "type": "talk",
      "dialogue": "し、刺激…？",
      "char": "c000_01",
      "speaker": "same",
      "pos": "left"
    },
    "13": {
      "type": "talk",
      "dialogue": "<color=ff1493>ウィー！\\<color=ff1493>これから我々は、《バンビーナ》を捕まえます！",
      "char": "c107_01",
      "speaker": "same",
      "pos": "right"
    },
    "14": {
      "type": "talk",
      "dialogue": "ば、ばんび…？\\何を捕まえるって？",
      "char": "c000_01",
      "speaker": "same",
      "pos": "left",
      "facial": "confused"
    },
    "15": {
      "type": "talk",
      "dialogue": "「女の子」って意味ですよ♥\\つまりナンパですね。\\ご主人さまも彼と一緒に出かけてみては？",
      "char": "c001_01",
      "speaker": "same",
      "pos": "right"
    },
    "16": {
      "type": "talk",
      "dialogue": "ああ、刺激ってそういう…\\だったら一人で…って、\\おい待て、お前ら部屋から押し出すんじゃない！？",
      "char": "c000_01",
      "speaker": "same",
      "pos": "left",
      "facial": "confused",
      "before_effect": "shake"
    },
    "17": {
      "type": "curtain",
      "background": "back",
      "wait": "normal",
      "fade_in": "normal"
    },
    "18": {
      "type": "curtain",
      "background": "back",
      "fade_out": "normal",
      "wait": "normal",
      "fade_in": "normal"
    },
    "19": {
      "type": "talk",
      "dialogue": "<color=ff1493>トレビアーン！\\<color=ff1493>女神の様な美しい髪をもつそこの少女！",
      "background": "bg011_f",
      "char": "c107_01",
      "speaker": "same",
      "pos": "center"
    },
    "20": {
      "type": "talk",
      "dialogue": "うっ…葉っぱが俺の頭に当たってる…",
      "char": "c000_01",
      "speaker": "same",
      "pos": "left",
      "facial": "nonsense"
    },
    "21": {
      "type": "talk",
      "dialogue": "<color=ff1493>その冷たい表情！とってもセクシーです！！",
      "char": "c107_01",
      "speaker": "same",
      "pos": "center"
    },
    "22": {
      "type": "talk",
      "dialogue": "<color=ff1493>緊張されているのですか、バンビーナ…♥",
      "char": "keep",
      "speaker": "same",
      "pos": "center",
      "distance": "near"
    },
    "23": {
      "type": "talk",
      "dialogue": "うざい…うせろ。",
      "char": "c048_00",
      "speaker": "same_full",
      "pos": "right",
      "before_effect": "shake"
    },
    "24": {
      "type": "talk",
      "dialogue": "<color=ff1493>う…うせろだなんて…",
      "char": "c107_01",
      "speaker": "same",
      "pos": "center"
    },
    "25": {
      "type": "talk",
      "dialogue": "残念だったな。\\まぁ、お前の姿が見える女が、\\普通の女だと思うか？",
      "char": "c000_01",
      "speaker": "same",
      "pos": "left",
      "facial": "idle"
    },
    "26": {
      "type": "talk",
      "dialogue": "<color=ff1493>ジュネ…",
      "char": "c107_01",
      "speaker": "same",
      "pos": "center"
    },
    "27": {
      "type": "talk",
      "dialogue": "俺にも分かるように話せよ…",
      "char": "c000_01",
      "speaker": "same",
      "pos": "left",
      "facial": "irritation"
    },
    "28": {
      "type": "talk",
      "dialogue": "<color=ff1493>…私には、よ、よく分かりません…",
      "char": "c107_01",
      "speaker": "same",
      "pos": "center",
      "loop_ani": "attack"
    },
    "29": {
      "type": "talk",
      "dialogue": "お前の姿が見える女性たちはな…？",
      "char": "c000_01",
      "speaker": "same",
      "pos": "left"
    },
    "30": {
      "type": "talk",
      "dialogue": "みんな正気じゃなかったり、\\悪魔に関係した恐ろしい女たちってことだ。",
      "char": "keep",
      "speaker": "same",
      "pos": "left",
      "facial": "haah"
    },
    "31": {
      "type": "talk",
      "dialogue": "<color=ff1493>そ、そんなっ！",
      "char": "c107_01",
      "speaker": "same",
      "pos": "center",
      "before_effect": "shake"
    },
    "32": {
      "type": "talk",
      "dialogue": "お前の描いている未来がどんなだか知らないが、\\これが現実だ。",
      "char": "c000_01",
      "speaker": "same",
      "pos": "left"
    },
    "33": {
      "type": "talk",
      "dialogue": "分かったならもう諦め…",
      "char": "keep",
      "speaker": "same",
      "pos": "left"
    },
    "34": {
      "type": "talk",
      "dialogue": "あっ…",
      "char": "keep",
      "speaker": "same",
      "pos": "left",
      "facial": "nonsense"
    },
    "35": {
      "type": "talk",
      "dialogue": "<color=ff1493>そこの、バンビーナ！！",
      "char": "c107_01",
      "speaker": "same",
      "pos": "center",
      "before_effect": "shake"
    },
    "36": {
      "type": "talk",
      "dialogue": "どけ。",
      "char": "c142_00",
      "speaker": "same_full",
      "pos": "right"
    },
    "37": {
      "type": "talk",
      "dialogue": "こりない奴だな…",
      "char": "c000_01",
      "speaker": "same",
      "pos": "left",
      "distance": "normal",
      "facial": "sigh"
    },
    "38": {
      "type": "curtain",
      "background": "back",
      "fade_out": "normal",
      "wait": "normal",
      "fade_in": "normal"
    }
  }
}