{
  "phase1": {
    "1": {
      "type": "talk",
      "dialogue": "拠点防衛もサポーターの重要な任務ですか…\\なるほど。",
      "background": "bg119_f",
      "bgm": "2",
      "char": "c002_01",
      "speaker": "same",
      "pos": "right",
      "facial": "pretense",
      "voiceid": "108702014"
    },
    "2": {
      "type": "talk",
      "dialogue": "子供を騙すスキルにどんどん磨きをかけているようですね。",
      "char": "keep",
      "speaker": "same",
      "pos": "right",
      "facial": "smile",
      "voiceid": "108702015"
    },
    "3": {
      "type": "talk",
      "dialogue": "ああいうピュアさを見ると、たまらなく\\なっちゃうの♥\\まだまだイジリ足りない気分よ～？",
      "char": "c001_01",
      "speaker": "same",
      "pos": "left",
      "facial": "smile",
      "voiceid": "108702016"
    },
    "4": {
      "type": "talk",
      "dialogue": "それじゃ、最高のエンターテイメント、悪魔たちの青春群像劇を見に行くとしましょうか～♥",
      "char": "keep",
      "speaker": "same",
      "pos": "left",
      "facial": "tempt",
      "voiceid": "108702017"
    },
    "5": {
      "type": "talk",
      "dialogue": "他人事のように言いますね…",
      "char": "c002_01",
      "speaker": "same",
      "pos": "right",
      "facial": "idle",
      "voiceid": "108702018"
    },
    "6": {
      "type": "talk",
      "dialogue": "ええ、そうよ。\\だって他人事でしょ～違うの？",
      "char": "c001_01",
      "speaker": "same",
      "pos": "left",
      "facial": "pretense",
      "voiceid": "108702019"
    },
    "7": {
      "type": "talk",
      "dialogue": "なるほど。確かにそうかもしれません。",
      "char": "c002_01",
      "speaker": "same",
      "pos": "right",
      "facial": "pretense",
      "voiceid": "108702020"
    },
    "8": {
      "type": "curtain",
      "background": "back",
      "fade_out": "normal",
      "wait": "normal",
      "fade_in": "normal"
    }
  }
}