{
  "phase1": {
    "1": {
      "type": "talk",
      "dialogue": "…",
      "background": "bg103_f",
      "bgm": "9",
      "char": "c002_01",
      "speaker": "same",
      "facial": "irritation",
      "voiceid": "107601001"
    },
    "2": {
      "type": "talk",
      "dialogue": "少し前にしたいたずらのせいか、リザが一日中\\不機嫌である。",
      "char": "none",
      "speaker": "none",
      "screen_effect": "dark",
      "voiceid": "107601002"
    },
    "3": {
      "type": "talk",
      "dialogue": "おはよう、リザ！\\今日も元気に行ってみようか、ハハハ…",
      "char": "c000_01",
      "speaker": "same",
      "pos": "left",
      "facial": "joy",
      "screen_effect": "none",
      "voiceid": "107601003"
    },
    "4": {
      "type": "talk",
      "dialogue": "はい、元気にいきましょう。",
      "char": "c002_01",
      "speaker": "same",
      "pos": "right",
      "distance": "near",
      "facial": "smile",
      "voiceid": "107601004"
    },
    "5": {
      "type": "talk",
      "dialogue": "おお、リザ！\\キゲンを直してくれたんだな、よかった！",
      "char": "c000_01",
      "speaker": "same",
      "pos": "left",
      "facial": "smile",
      "voiceid": "107601005"
    },
    "6": {
      "type": "talk",
      "dialogue": "ええ、元気にいきましょう。\\サキュバス魔神と一緒に。",
      "char": "c002_01",
      "speaker": "same",
      "pos": "right",
      "facial": "smile",
      "voiceid": "107601006"
    },
    "7": {
      "type": "talk",
      "dialogue": "まだ拗ねてるじゃん！",
      "char": "c000_01",
      "speaker": "same",
      "pos": "left",
      "facial": "unfair",
      "screen_effect": "shake",
      "voiceid": "107601007"
    },
    "8": {
      "type": "talk",
      "dialogue": "あと魔神じゃなくて、《魔王666号》だよ。",
      "char": "keep",
      "speaker": "same",
      "pos": "left",
      "facial": "irritation",
      "voiceid": "107601008"
    },
    "9": {
      "type": "talk",
      "dialogue": "…もう、怒りのゲージを振り切って、なんの感情も\\湧いてきません…",
      "char": "c002_01",
      "speaker": "same",
      "pos": "right",
      "voiceid": "107601009"
    },
    "10": {
      "type": "curtain",
      "background": "back",
      "fade_out": "normal",
      "wait": "normal",
      "fade_in": "normal"
    }
  }
}